odoo/addons/fleet_vehicle_ownership/README.rst
odoo/addons/fleet_vehicle_ownership/__init__.py
odoo/addons/fleet_vehicle_ownership/__manifest__.py
odoo/addons/fleet_vehicle_ownership/demo/fleet_vehicle.xml
odoo/addons/fleet_vehicle_ownership/i18n/es.po
odoo/addons/fleet_vehicle_ownership/i18n/fleet_vehicle_ownership.pot
odoo/addons/fleet_vehicle_ownership/i18n/it.po
odoo/addons/fleet_vehicle_ownership/i18n/pt_BR.po
odoo/addons/fleet_vehicle_ownership/models/__init__.py
odoo/addons/fleet_vehicle_ownership/models/fleet_vehicle.py
odoo/addons/fleet_vehicle_ownership/models/res_partner.py
odoo/addons/fleet_vehicle_ownership/readme/CONTEXT.md
odoo/addons/fleet_vehicle_ownership/readme/CONTRIBUTORS.md
odoo/addons/fleet_vehicle_ownership/readme/DESCRIPTION.md
odoo/addons/fleet_vehicle_ownership/readme/USAGE.md
odoo/addons/fleet_vehicle_ownership/static/description/icon.png
odoo/addons/fleet_vehicle_ownership/static/description/index.html
odoo/addons/fleet_vehicle_ownership/tests/__init__.py
odoo/addons/fleet_vehicle_ownership/tests/test_fleet_vehicle_owner.py
odoo/addons/fleet_vehicle_ownership/views/fleet_vehicle.xml
odoo/addons/fleet_vehicle_ownership/views/res_partner.xml
odoo14_addon_fleet_vehicle_ownership-14.0.1.0.1.dev8.dist-info/METADATA
odoo14_addon_fleet_vehicle_ownership-14.0.1.0.1.dev8.dist-info/WHEEL
odoo14_addon_fleet_vehicle_ownership-14.0.1.0.1.dev8.dist-info/top_level.txt
odoo14_addon_fleet_vehicle_ownership-14.0.1.0.1.dev8.dist-info/RECORD
